billomat/__init__.py
billomat/base.py
billomat/fields.py
billomat/mixins.py
billomat/models.py
billomat/tests/__init__.py
billomat/tests/test_client.py
billomat/tests/test_queryset.py
billomat-0.1.32.dist-info/LICENSE.md
billomat-0.1.32.dist-info/METADATA
billomat-0.1.32.dist-info/WHEEL
billomat-0.1.32.dist-info/top_level.txt
billomat-0.1.32.dist-info/RECORD
