Metadata-Version: 2.1
Name: billomat
Version: 0.1.32
Summary: billomat.com API client
Home-page: http://jensnistler.de/
Author: Jens Nistler
Author-email: opensource@jensnistler.de
License: MIT
Download-URL: http://github.com/lociii/billomat
Keywords: billomat,api,client
Platform: UNKNOWN
Classifier: Programming Language :: Python
Classifier: Programming Language :: Python :: 2
Classifier: Development Status :: 3 - Alpha
Classifier: Intended Audience :: Developers
Classifier: License :: OSI Approved :: MIT License
Classifier: Operating System :: OS Independent
Classifier: Topic :: Software Development
Requires-Dist: httmock (>=1.0.7)
Requires-Dist: mock (>=1.0.1)
Requires-Dist: python-dateutil (>=2.2)
Requires-Dist: requests (>=2.1.0)
Requires-Dist: six (>=1.4.1)
